prompt_wrangler/__init__.py
prompt_wrangler/client.py
prompt_wrangler/client.pyi
prompt_wrangler/prompt_wrangler.py
prompt_wrangler/__pycache__/__init__.cpython-310.pyc
prompt_wrangler/__pycache__/client.cpython-310.pyc
prompt_wrangler-0.5.0.dist-info/METADATA
prompt_wrangler-0.5.0.dist-info/WHEEL
prompt_wrangler-0.5.0.dist-info/top_level.txt
prompt_wrangler-0.5.0.dist-info/RECORD
