Metadata-Version: 2.1
Name: prompt-wrangler
Version: 0.5.0
Summary: A Python wrapper for the Prompt Wrangler REST API.
Home-page: UNKNOWN
Author: Max Shaw
Author-email: max@exit38.org
License: UNKNOWN
Platform: UNKNOWN
Classifier: Development Status :: 3 - Alpha
Classifier: Intended Audience :: Developers
Classifier: License :: OSI Approved :: MIT License
Classifier: Programming Language :: Python :: 3
Classifier: Programming Language :: Python :: 3.6
Classifier: Programming Language :: Python :: 3.7
Classifier: Programming Language :: Python :: 3.8
Classifier: Programming Language :: Python :: 3.9
Requires-Python: >=3.6
Requires-Dist: requests
